qianqiuyun/__init__.py
qianqiuyun/sdk/__init__.py
qianqiuyun/sdk/mq.py
qianqiuyun/sdk/sql.py
qianqiuyun/sdk/tsdb.py
qianqiuyun-1.0.0.dist-info/LICENSE
qianqiuyun-1.0.0.dist-info/METADATA
qianqiuyun-1.0.0.dist-info/WHEEL
qianqiuyun-1.0.0.dist-info/top_level.txt
qianqiuyun-1.0.0.dist-info/RECORD
