Metadata-Version: 2.1
Name: qianqiuyun
Version: 1.0.0
Summary: qianqiuyun sdk
Author: qianqiusoft
Author-email: develop@qianqiusoft.com
Classifier: Programming Language :: Python :: 3
Classifier: License :: OSI Approved :: MIT License
Classifier: Operating System :: OS Independent
Requires-Python: >=3
License-File: LICENSE
Requires-Dist: pymysql
Requires-Dist: nats-py
Requires-Dist: influxdb
